budou/__init__.py
budou/__version__.py
budou/budou.py
budou/cachefactory.py
budou/chunk.py
budou/mecabsegmenter.py
budou/nlapisegmenter.py
budou/parser.py
budou/segmenter.py
budou/tinysegmentersegmenter.py
budou-0.9.8.dist-info/LICENSE
budou-0.9.8.dist-info/METADATA
budou-0.9.8.dist-info/WHEEL
budou-0.9.8.dist-info/entry_points.txt
budou-0.9.8.dist-info/top_level.txt
budou-0.9.8.dist-info/RECORD
