Metadata-Version: 2.1
Name: budou
Version: 0.9.8
Summary: CJK Line Break Organizer
Home-page: https://github.com/google/budou/
Author: Shuhei Iitsuka
Author-email: tushuhei@google.com
License: Apache
Platform: UNKNOWN
Classifier: Development Status :: 3 - Alpha
Classifier: Operating System :: OS Independent
Classifier: Programming Language :: Python
Classifier: License :: OSI Approved :: Apache Software License
Classifier: Topic :: Software Development :: Libraries :: Python Modules
Requires-Dist: chardet
Requires-Dist: docopt
Requires-Dist: future
Requires-Dist: google-api-python-client
Requires-Dist: google-auth-httplib2
Requires-Dist: google-auth (>=1.0.0)
Requires-Dist: html5lib (==1.0.1)
Requires-Dist: six
Requires-Dist: tinysegmenter3
Requires-Dist: urllib3
